MANIFEST.in
README.rst
setup.py
Djaloha.egg-info/PKG-INFO
Djaloha.egg-info/SOURCES.txt
Djaloha.egg-info/dependency_links.txt
Djaloha.egg-info/not-zip-safe
Djaloha.egg-info/requires.txt
Djaloha.egg-info/top_level.txt
djaloha/__init__.py
djaloha/forms.py
djaloha/tests.py
djaloha/urls.py
djaloha/utils.py
djaloha/views.py
djaloha/widgets.py
djaloha/locale/fr/LC_MESSAGES/django.mo
djaloha/locale/fr/LC_MESSAGES/django.po
djaloha/static/aloha.0.20/build.txt
djaloha/static/aloha.0.20/package.json
djaloha/static/aloha.0.20/css/aloha-core.css
djaloha/static/aloha.0.20/css/aloha-sidebar.css
djaloha/static/aloha.0.20/css/aloha.css
djaloha/static/aloha.0.20/css/ext-aloha-reset.css
djaloha/static/aloha.0.20/css/ext-aloha.css
djaloha/static/aloha.0.20/img/arrow-down.png
djaloha/static/aloha.0.20/img/arrow-left.png
djaloha/static/aloha.0.20/img/arrow.png
djaloha/static/aloha.0.20/img/base-big.png
djaloha/static/aloha.0.20/img/base-multi.png
djaloha/static/aloha.0.20/img/base.png
djaloha/static/aloha.0.20/img/bg.png
djaloha/static/aloha.0.20/img/breadcrumb-divider.png
djaloha/static/aloha.0.20/img/fade-in.png
djaloha/static/aloha.0.20/img/fade-out.png
djaloha/static/aloha.0.20/img/gentics-logo.png
djaloha/static/aloha.0.20/img/grabhandle.png
djaloha/static/aloha.0.20/img/maximize.png
djaloha/static/aloha.0.20/img/multisplit-base.jpg
djaloha/static/aloha.0.20/img/multisplit-close.gif
djaloha/static/aloha.0.20/img/multisplit-open.gif
djaloha/static/aloha.0.20/img/pin.png
djaloha/static/aloha.0.20/img/removeformat.png
djaloha/static/aloha.0.20/img/text_indent.png
djaloha/static/aloha.0.20/img/text_indent_remove.png
djaloha/static/aloha.0.20/lib/aloha-bootstrap.js
djaloha/static/aloha.0.20/lib/aloha.js
djaloha/static/aloha.0.20/lib/css.js
djaloha/static/aloha.0.20/lib/i18n.js
djaloha/static/aloha.0.20/lib/jquery-plugin.js
djaloha/static/aloha.0.20/lib/order.js
djaloha/static/aloha.0.20/lib/require.js
djaloha/static/aloha.0.20/lib/text.js
djaloha/static/aloha.0.20/lib/aloha/command.js
djaloha/static/aloha.0.20/lib/aloha/console.js
djaloha/static/aloha.0.20/lib/aloha/contenthandlermanager.js
djaloha/static/aloha.0.20/lib/aloha/core.js
