Metadata-Version: 1.0
Name: Djaloha
Version: 0.4.1
Summary: Django integration for aloha HTML5 editor
Home-page: UNKNOWN
Author: Luc Jean
Author-email: ljean@apidev.fr
License: BSD
Platform: UNKNOWN
